{
  "kind": "collectionType",
  "collectionName": "categories",
  "info": {
    "name": "category",
    "description": ""
  },
  "options": {
    "increments": true,
    "timestamps": true,
    "draftAndPublish": true
  },
  "pluginOptions": {},
  "attributes": {
    "cid": {
      "type": "integer"
    },
    "name": {
      "type": "string"
    },
    "size": {
      "type": "string"
    },
    "remote_url": {
      "type": "string"
    },
    "local_url": {
      "type": "string"
    },
    "link_url": {
      "type": "string"
    }
  }
}
